CeleryFlask/__init__.py
CeleryFlask-0.0.2.dist-info/LICENSE
CeleryFlask-0.0.2.dist-info/METADATA
CeleryFlask-0.0.2.dist-info/WHEEL
CeleryFlask-0.0.2.dist-info/top_level.txt
CeleryFlask-0.0.2.dist-info/RECORD
