Metadata-Version: 2.1
Name: CeleryFlask
Version: 0.0.2
Summary: Extension Flask for integration with celery
Home-page: https://github.com/ganggas95/celery-flask
Author: Ganggas95
Author-email: subhannizar25@gmail.com
License: MIT
Platform: UNKNOWN
Classifier: Programming Language :: Python :: 3
Classifier: License :: OSI Approved :: MIT License
Classifier: Operating System :: OS Independent
Classifier: Topic :: Software Development :: Libraries :: Python Modules
Classifier: Topic :: Database
Requires-Dist: Flask (>=1.0)
Requires-Dist: Celery (>=4.4.0)
